pywgetb3/__init__.py
pywgetb3-0.0.1.dist-info/WHEEL
pywgetb3-0.0.1.dist-info/METADATA
pywgetb3-0.0.1.dist-info/RECORD
