Metadata-Version: 2.1
Name: pywgetb3
Version: 0.0.1
Summary: This module do download from b3 historical data.
Home-page: https://github.com/guifabrin/pywgetb3
Author: Guilherme Fabrin Franco
Author-email: guilherme.fabrin@gmail.com
Classifier: License :: OSI Approved :: MIT License
